lib/__init__.py
lib/resistorcalc.py
lib/test.py
resistorcalc-0.0.2.dist-info/METADATA
resistorcalc-0.0.2.dist-info/WHEEL
resistorcalc-0.0.2.dist-info/top_level.txt
resistorcalc-0.0.2.dist-info/RECORD
