Metadata-Version: 2.1
Name: resistorcalc
Version: 0.0.2
Summary: The ResistorCal is an tool used to find the resistor values by giving the input colors
Home-page: UNKNOWN
Author: Hariharan C
License: UNKNOWN
Keywords: resistor value calculator,color code resistor calculator,resistor color to value,resistor code decoder,Electronics,Resistor value finder,color code,color bands,numeric values,calculate resistor value from color bands,online resistor color code tool,how to identify resistor value by color,resistor value conversion tool,resistorcal,resistorcal tool,resistorcal color code calculator,electronics component calculator,electrical engineering tool,color code to resistance converter,electronic 
Platform: UNKNOWN
